MANIFEST.in
README.md
VERSION
requirements.txt
setup.cfg
setup.py
rhasspy_tts_wavenet_hermes.egg-info/PKG-INFO
rhasspy_tts_wavenet_hermes.egg-info/SOURCES.txt
rhasspy_tts_wavenet_hermes.egg-info/dependency_links.txt
rhasspy_tts_wavenet_hermes.egg-info/entry_points.txt
rhasspy_tts_wavenet_hermes.egg-info/requires.txt
rhasspy_tts_wavenet_hermes.egg-info/top_level.txt
rhasspytts_wavenet_hermes/__init__.py
rhasspytts_wavenet_hermes/__main__.py